valar_app_mixins/__init__.py
valar_app_mixins/auto_migration_mixin.py
valar_app_mixins/auto_urlpatterns_mixin.py
valar_auto_mixins-0.0.1.dist-info/METADATA
valar_auto_mixins-0.0.1.dist-info/WHEEL
valar_auto_mixins-0.0.1.dist-info/top_level.txt
valar_auto_mixins-0.0.1.dist-info/RECORD
