Metadata-Version: 2.4
Name: valar_auto_mixins
Version: 0.0.1
Summary: valar auto mixins
Home-page: https://gitee.com/GRIFFIN120
Author: LYP
Author-email: liuyinpeng@buaa.edu.cn
Requires-Python: >=3.9
Requires-Dist: Django~=4.2.20
Dynamic: author
Dynamic: author-email
Dynamic: description
Dynamic: description-content-type
Dynamic: home-page
Dynamic: requires-dist
Dynamic: requires-python
Dynamic: summary
